README.rst
setup.py
typesafe_conductr_cli/__init__.py
typesafe_conductr_cli/bundle_utils.py
typesafe_conductr_cli/conduct.py
typesafe_conductr_cli/conduct_info.py
typesafe_conductr_cli/conduct_load.py
typesafe_conductr_cli/conduct_logging.py
typesafe_conductr_cli/conduct_run.py
typesafe_conductr_cli/conduct_services.py
typesafe_conductr_cli/conduct_stop.py
typesafe_conductr_cli/conduct_unload.py
typesafe_conductr_cli/conduct_url.py
typesafe_conductr_cli/conduct_version.py
typesafe_conductr_cli/shazar.py
typesafe_conductr_cli.egg-info/PKG-INFO
typesafe_conductr_cli.egg-info/SOURCES.txt
typesafe_conductr_cli.egg-info/dependency_links.txt
typesafe_conductr_cli.egg-info/entry_points.txt
typesafe_conductr_cli.egg-info/requires.txt
typesafe_conductr_cli.egg-info/top_level.txt
typesafe_conductr_cli/test/__init__.py
typesafe_conductr_cli/test/cli_test_case.py
typesafe_conductr_cli/test/test_bundle_utils.py
typesafe_conductr_cli/test/test_conduct.py
typesafe_conductr_cli/test/test_conduct_info.py
typesafe_conductr_cli/test/test_conduct_load.py
typesafe_conductr_cli/test/test_conduct_run.py
typesafe_conductr_cli/test/test_conduct_services.py
typesafe_conductr_cli/test/test_conduct_stop.py
typesafe_conductr_cli/test/test_conduct_unload.py
typesafe_conductr_cli/test/test_shazar.py