Metadata-Version: 1.0
Name: typesafe-conductr-cli
Version: 0.8
Summary: A CLI client for Typesafe ConductR
Home-page: https://github.com/typesafehub/typesafe-conductr-cli
Author: UNKNOWN
Author-email: UNKNOWN
License: Apache 2
Platform: UNKNOWN
